httpx_aiohttp/__init__.py
httpx_aiohttp/client.py
httpx_aiohttp/py.typed
httpx_aiohttp/transport.py
httpx_aiohttp-0.1.11.dist-info/METADATA
httpx_aiohttp-0.1.11.dist-info/WHEEL
httpx_aiohttp-0.1.11.dist-info/licenses/LICENSE
httpx_aiohttp-0.1.11.dist-info/RECORD
