Metadata-Version: 2.4
Name: httpx-aiohttp
Version: 0.1.11
Summary: Aiohttp transport for HTTPX
Project-URL: Homepage, https://karpetrosyan.github.io/httpx-aiohttp/
Project-URL: Source, https://github.com/karpetrosyan/httpx-aiohttp
Author-email: Karen Petrosyan <kar.petrosyanpy@gmail.com>
License: Copyright © 2025, Karen Petrosyan.
License-File: LICENSE
Requires-Python: >=3.8
Requires-Dist: aiohttp<4,>=3.10.0
Requires-Dist: httpx>=0.27.0
